bn_testing/__init__.py
bn_testing/conditionals.py
bn_testing/dags.py
bn_testing/helpers.py
bn_testing/models.py
bn_testing/terms.py
bn_testing-0.12.2.dist-info/LICENSE
bn_testing-0.12.2.dist-info/METADATA
bn_testing-0.12.2.dist-info/WHEEL
bn_testing-0.12.2.dist-info/top_level.txt
bn_testing-0.12.2.dist-info/RECORD
