Metadata-Version: 2.1
Name: bn-testing
Version: 0.12.2
Summary: A test bench to benchmark learn algorithms for graphical models
Home-page: https://github.com/windisch/bn_testing
Author: Tobias Windisch
Author-email: tobias.windisch@posteo.de
License: Apache-2.0
Keywords: graphical models
Requires-Python: >=3.8.0
License-File: LICENSE
Requires-Dist: numpy (>=1.23.0)
Requires-Dist: pandas (>=1.5.0)
Requires-Dist: networkx (>=2.5)
Requires-Dist: pymc (>4.2.0)
Requires-Dist: pytensor (>=2.12.1)
Requires-Dist: cloudpickle
Requires-Dist: aesara
